action_msgs/_dummy.cpython-310-x86_64-linux-gnu.so
ros_action_msgs-2.3.0.data/data/include/action_msgs/action_msgs/msg/goal_info.h
ros_action_msgs-2.3.0.data/data/include/action_msgs/action_msgs/msg/goal_info.hpp
ros_action_msgs-2.3.0.data/data/include/action_msgs/action_msgs/msg/goal_status.h
ros_action_msgs-2.3.0.data/data/include/action_msgs/action_msgs/msg/goal_status.hpp
ros_action_msgs-2.3.0.data/data/include/action_msgs/action_msgs/msg/goal_status_array.h
ros_action_msgs-2.3.0.data/data/include/action_msgs/action_msgs/msg/goal_status_array.hpp
ros_action_msgs-2.3.0.data/data/include/action_msgs/action_msgs/msg/rosidl_generator_c__visibility_control.h
ros_action_msgs-2.3.0.data/data/include/action_msgs/action_msgs/msg/rosidl_generator_cpp__visibility_control.hpp
ros_action_msgs-2.3.0.data/data/include/action_msgs/action_msgs/msg/rosidl_typesupport_fastrtps_c__visibility_control.h
ros_action_msgs-2.3.0.data/data/include/action_msgs/action_msgs/msg/rosidl_typesupport_fastrtps_cpp__visibility_control.h
ros_action_msgs-2.3.0.data/data/include/action_msgs/action_msgs/msg/rosidl_typesupport_introspection_c__visibility_control.h
ros_action_msgs-2.3.0.data/data/include/action_msgs/action_msgs/msg/detail/goal_info__builder.hpp
ros_action_msgs-2.3.0.data/data/include/action_msgs/action_msgs/msg/detail/goal_info__description.c
ros_action_msgs-2.3.0.data/data/include/action_msgs/action_msgs/msg/detail/goal_info__functions.c
ros_action_msgs-2.3.0.data/data/include/action_msgs/action_msgs/msg/detail/goal_info__functions.h
ros_action_msgs-2.3.0.data/data/include/action_msgs/action_msgs/msg/detail/goal_info__rosidl_typesupport_fastrtps_c.h
ros_action_msgs-2.3.0.data/data/include/action_msgs/action_msgs/msg/detail/goal_info__rosidl_typesupport_fastrtps_cpp.hpp
ros_action_msgs-2.3.0.data/data/include/action_msgs/action_msgs/msg/detail/goal_info__rosidl_typesupport_introspection_c.h
ros_action_msgs-2.3.0.data/data/lib/python3.10/site-packages/action_msgs-2.3.0-py3.10.egg-info/PKG-INFO
ros_action_msgs-2.3.0.data/data/lib/python3.10/site-packages/action_msgs-2.3.0-py3.10.egg-info/SOURCES.txt
ros_action_msgs-2.3.0.data/data/lib/python3.10/site-packages/action_msgs-2.3.0-py3.10.egg-info/dependency_links.txt
ros_action_msgs-2.3.0.data/data/lib/python3.10/site-packages/action_msgs-2.3.0-py3.10.egg-info/top_level.txt
ros_action_msgs-2.3.0.dist-info/METADATA
ros_action_msgs-2.3.0.dist-info/WHEEL
ros_action_msgs-2.3.0.dist-info/top_level.txt
ros_action_msgs-2.3.0.dist-info/RECORD
