Metadata-Version: 2.4
Name: ros-action-msgs
Version: 2.3.0
Summary: ROS 2 package providing essential messages and services for managing action goals and their statuses.
Requires-Dist: ros-unique-identifier-msgs~=2.7.0
Requires-Dist: ros-service-msgs~=2.3.0
Requires-Dist: ros-rosidl-core-runtime~=0.3.1
Requires-Dist: ros-builtin-interfaces~=2.3.0
Dynamic: description
Dynamic: description-content-type
Dynamic: requires-dist
Dynamic: summary
